proxybroker/__init__.py
proxybroker/api.py
proxybroker/checker.py
proxybroker/cli.py
proxybroker/errors.py
proxybroker/judge.py
proxybroker/negotiators.py
proxybroker/providers.py
proxybroker/proxy.py
proxybroker/resolver.py
proxybroker/server.py
proxybroker/utils.py
proxybroker/data/GeoLite2-Country.mmdb
proxybroker/data/__init__.py
proxybroker-0.3.2.dist-info/LICENSE
proxybroker-0.3.2.dist-info/METADATA
proxybroker-0.3.2.dist-info/WHEEL
proxybroker-0.3.2.dist-info/entry_points.txt
proxybroker-0.3.2.dist-info/top_level.txt
proxybroker-0.3.2.dist-info/RECORD
