Metadata-Version: 1.2
Name: proxybroker
Version: 0.3.2
Summary: [Finder/Checker/Server] Finds public proxies from multiple sources and concurrently checks them. Supports HTTP(S) and SOCKS4/5.
Home-page: https://github.com/constverum/ProxyBroker
Author: Constverum
Author-email: constverum@gmail.com
License: Apache License, Version 2.0
Keywords: proxy finder grabber scraper parser graber scrapper checker broker async asynchronous http https connect socks socks4 socks5
Platform: any
Classifier: Development Status :: 5 - Production/Stable
Classifier: Environment :: Console
Classifier: Environment :: Web Environment
Classifier: Intended Audience :: Developers
Classifier: Programming Language :: Python :: 3.5
Classifier: Programming Language :: Python :: 3.6
Classifier: Operating System :: POSIX
Classifier: Operating System :: MacOS :: MacOS X
Classifier: Operating System :: Microsoft :: Windows
Classifier: Topic :: Internet :: WWW/HTTP :: Indexing/Search
Classifier: Topic :: Internet :: Proxy Servers
Classifier: License :: OSI Approved :: Apache Software License
Requires-Python: >=3.5.3
